[
    {
        "kind": "youtube#searchResult",
        "etag": "\"nxOHAKTVB7baOKsQgTtJIyGxcs8/Of3CpEmpDne3m1RbyOIPqPKo7P0\"",
        "id": {
            "kind": "youtube#video",
            "videoId": "jiUKeCLMS90"
        },
        "snippet": {
            "publishedAt": "2011-08-09T22:32:13.000Z",
            "channelId": "UC0aBuqqUobPX8oW8whmX2_g",
            "title": "Surgery Video: Carpal Tunnel - MedStar Union Memorial",
            "description": "[GRAPHIC CONTENT WARNING: Surgical Procedure] Dr. Keith Segalman, a hand surgeon from MedStar Union Memorial Hospital's Curtis National Hand ...",
            "thumbnails": {
                "default": {
                    "url": "https://i.ytimg.com/vi/jiUKeCLMS90/default.jpg",
                    "width": 120,
                    "height": 90
                },
                "medium": {
                    "url": "https://i.ytimg.com/vi/jiUKeCLMS90/mqdefault.jpg",
                    "width": 320,
                    "height": 180
                },
                "high": {
                    "url": "https://i.ytimg.com/vi/jiUKeCLMS90/hqdefault.jpg",
                    "width": 480,
                    "height": 360
                }
            },
            "channelTitle": "MedStar Health",
            "liveBroadcastContent": "none"
        }
    },
    {
        "kind": "youtube#searchResult",
        "etag": "\"nxOHAKTVB7baOKsQgTtJIyGxcs8/0LJUP9t6rgn8I2ELHB4jYJNb0UQ\"",
        "id": {
            "kind": "youtube#video",
            "videoId": "isYY2jvd8PU"
        },
        "snippet": {
            "publishedAt": "2020-03-11T20:29:58.000Z",
            "channelId": "UChIIig54yF9aQYvpWGe1DPg",
            "title": "Live Surgery: Deep Brain Stimulation - Ryder P. Gwinn, MD",
            "description": "http://www.seattlesciencefoundation.org Seattle Science Foundation is a non-profit organization dedicated to the international collaboration among physicians, ...",
            "thumbnails": {
                "default": {
                    "url": "https://i.ytimg.com/vi/isYY2jvd8PU/default.jpg",
                    "width": 120,
                    "height": 90
                },
                "medium": {
                    "url": "https://i.ytimg.com/vi/isYY2jvd8PU/mqdefault.jpg",
                    "width": 320,
                    "height": 180
                },
                "high": {
                    "url": "https://i.ytimg.com/vi/isYY2jvd8PU/hqdefault.jpg",
                    "width": 480,
                    "height": 360
                }
            },
            "channelTitle": "Seattle Science Foundation",
            "liveBroadcastContent": "none"
        }
    },
    {
        "kind": "youtube#searchResult",
        "etag": "\"nxOHAKTVB7baOKsQgTtJIyGxcs8/lQjZhqv-0XQMJNy-GNJXtRdADvw\"",
        "id": {
            "kind": "youtube#video",
            "videoId": "GQA8IRL5Gds"
        },
        "snippet": {
            "publishedAt": "2015-11-10T16:50:30.000Z",
            "channelId": "UC4ZyUot7ROY6H1kV8_J__kQ",
            "title": "Dr. Casden Performs Anterior Cervical Spine Surgery",
            "description": "In this video segment, Andrew Casden, MD, describes the history and MRI of a patient with a cervical disc herniation and performs the surgery with a descriptive ...",
            "thumbnails": {
                "default": {
                    "url": "https://i.ytimg.com/vi/GQA8IRL5Gds/default.jpg",
                    "width": 120,
                    "height": 90
                },
                "medium": {
                    "url": "https://i.ytimg.com/vi/GQA8IRL5Gds/mqdefault.jpg",
                    "width": 320,
                    "height": 180
                },
                "high": {
                    "url": "https://i.ytimg.com/vi/GQA8IRL5Gds/hqdefault.jpg",
                    "width": 480,
                    "height": 360
                }
            },
            "channelTitle": "Mount Sinai Health System",
            "liveBroadcastContent": "none"
        }
    },
    {
        "kind": "youtube#searchResult",
        "etag": "\"nxOHAKTVB7baOKsQgTtJIyGxcs8/HuLhljkxz7sMUjFIMAhtlo1VI1A\"",
        "id": {
            "kind": "youtube#video",
            "videoId": "dIdBaYA4s4o"
        },
        "snippet": {
            "publishedAt": "2020-04-08T15:00:33.000Z",
            "channelId": "UCTWEFB801fb7EYo7D-LrhzQ",
            "title": "Abdominal Wall Surgery",
            "description": "",
            "thumbnails": {
                "default": {
                    "url": "https://i.ytimg.com/vi/dIdBaYA4s4o/default.jpg",
                    "width": 120,
                    "height": 90
                },
                "medium": {
                    "url": "https://i.ytimg.com/vi/dIdBaYA4s4o/mqdefault.jpg",
                    "width": 320,
                    "height": 180
                },
                "high": {
                    "url": "https://i.ytimg.com/vi/dIdBaYA4s4o/hqdefault.jpg",
                    "width": 480,
                    "height": 360
                }
            },
            "channelTitle": "American Society of Plastic Surgeons ASPS",
            "liveBroadcastContent": "none"
        }
    },
    {
        "kind": "youtube#searchResult",
        "etag": "\"nxOHAKTVB7baOKsQgTtJIyGxcs8/TYlM5B8tIJIeS2xfcEhOCZqithQ\"",
        "id": {
            "kind": "youtube#video",
            "videoId": "u9TSMfvq4LY"
        },
        "snippet": {
            "publishedAt": "2020-01-21T23:12:13.000Z",
            "channelId": "UCEysNS1qaE8pS0w5CnC3YEA",
            "title": "Liver Transplant Surgery - UT Southwestern Medical Center - 2020",
            "description": "Join Dr. Parsia Vagefi, Chief of Surgical Transplantation and Dr. Steven Hanish, Surgical Director of Liver Transplantation, as they grant unprecedented access ...",
            "thumbnails": {
                "default": {
                    "url": "https://i.ytimg.com/vi/u9TSMfvq4LY/default.jpg",
                    "width": 120,
                    "height": 90
                },
                "medium": {
                    "url": "https://i.ytimg.com/vi/u9TSMfvq4LY/mqdefault.jpg",
                    "width": 320,
                    "height": 180
                },
                "high": {
                    "url": "https://i.ytimg.com/vi/u9TSMfvq4LY/hqdefault.jpg",
                    "width": 480,
                    "height": 360
                }
            },
            "channelTitle": "UTSWMed",
            "liveBroadcastContent": "none"
        }
    },
    {
        "kind": "youtube#searchResult",
        "etag": "\"nxOHAKTVB7baOKsQgTtJIyGxcs8/a86qqzkduLX1BAbdZlmWLT7BOrs\"",
        "id": {
            "kind": "youtube#video",
            "videoId": "zPXphpl7gco"
        },
        "snippet": {
            "publishedAt": "2020-03-12T17:15:46.000Z",
            "channelId": "UC8hzWaP0JfFJ8a1UjLIl1FA",
            "title": "Kidney Transplant Surgery | Inside the OR",
            "description": "Surgeon. Scalpel. Sock? Head #InsideTheOR and see how these three things come together in one very surprising way.",
            "thumbnails": {
                "default": {
                    "url": "https://i.ytimg.com/vi/zPXphpl7gco/default.jpg",
                    "width": 120,
                    "height": 90
                },
                "medium": {
                    "url": "https://i.ytimg.com/vi/zPXphpl7gco/mqdefault.jpg",
                    "width": 320,
                    "height": 180
                },
                "high": {
                    "url": "https://i.ytimg.com/vi/zPXphpl7gco/hqdefault.jpg",
                    "width": 480,
                    "height": 360
                }
            },
            "channelTitle": "Northwestern Medicine",
            "liveBroadcastContent": "none"
        }
    },
    {
        "kind": "youtube#searchResult",
        "etag": "\"nxOHAKTVB7baOKsQgTtJIyGxcs8/ScCm_Us9hYtXHeWKj1PvZVl8Pzw\"",
        "id": {
            "kind": "youtube#video",
            "videoId": "cKnw7HWzbGU"
        },
        "snippet": {
            "publishedAt": "2018-11-29T15:30:18.000Z",
            "channelId": "UCDp-ctduCmWgCjr5w68s4Cw",
            "title": "Cameron Underwood Face Transplant Surgical Animation 2018",
            "description": "Eduardo D. Rodriguez, MD, DDS, chair of the Hansj\u00f6rg Wyss Department of Plastic Surgery, and the Helen L. Kimmel Professor of Reconstructive Plastic ...",
            "thumbnails": {
                "default": {
                    "url": "https://i.ytimg.com/vi/cKnw7HWzbGU/default.jpg",
                    "width": 120,
                    "height": 90
                },
                "medium": {
                    "url": "https://i.ytimg.com/vi/cKnw7HWzbGU/mqdefault.jpg",
                    "width": 320,
                    "height": 180
                },
                "high": {
                    "url": "https://i.ytimg.com/vi/cKnw7HWzbGU/hqdefault.jpg",
                    "width": 480,
                    "height": 360
                }
            },
            "channelTitle": "NYU Langone Health",
            "liveBroadcastContent": "none"
        }
    },
    {
        "kind": "youtube#searchResult",
        "etag": "\"nxOHAKTVB7baOKsQgTtJIyGxcs8/I_OsD80JW7yQ7oq1ULXdsXC5X6E\"",
        "id": {
            "kind": "youtube#video",
            "videoId": "eYqOITSzne4"
        },
        "snippet": {
            "publishedAt": "2017-11-10T15:24:10.000Z",
            "channelId": "UCfp5MBK2IC90Bdm5IQUJvYw",
            "title": "Pre-surgery tour for patients at C.S. Mott Children&#39;s Hospital",
            "description": "Children and families can get a behind the scenes look at the pre-op areas and the operating rooms at C.S. Mott Children's Hospital to help them prepare and ...",
            "thumbnails": {
                "default": {
                    "url": "https://i.ytimg.com/vi/eYqOITSzne4/default.jpg",
                    "width": 120,
                    "height": 90
                },
                "medium": {
                    "url": "https://i.ytimg.com/vi/eYqOITSzne4/mqdefault.jpg",
                    "width": 320,
                    "height": 180
                },
                "high": {
                    "url": "https://i.ytimg.com/vi/eYqOITSzne4/hqdefault.jpg",
                    "width": 480,
                    "height": 360
                }
            },
            "channelTitle": "Michigan Medicine",
            "liveBroadcastContent": "none"
        }
    },
    {
        "kind": "youtube#searchResult",
        "etag": "\"nxOHAKTVB7baOKsQgTtJIyGxcs8/bGkt675yPZPOI41DidMpqXl7uuQ\"",
        "id": {
            "kind": "youtube#video",
            "videoId": "mKuoc0ZbKug"
        },
        "snippet": {
            "publishedAt": "2019-07-18T15:22:43.000Z",
            "channelId": "UCxyiSz4m161Z6frOsFxJpgw",
            "title": "Aortic Valve Surgery",
            "description": "Dr. Eric Roselli, Chief of Adult Cardiac Surgery, and Dr. Lars Svensson, Chairman of the Sydell and Arnold Miller Family Heart & Vascular Institute, talk about ...",
            "thumbnails": {
                "default": {
                    "url": "https://i.ytimg.com/vi/mKuoc0ZbKug/default.jpg",
                    "width": 120,
                    "height": 90
                },
                "medium": {
                    "url": "https://i.ytimg.com/vi/mKuoc0ZbKug/mqdefault.jpg",
                    "width": 320,
                    "height": 180
                },
                "high": {
                    "url": "https://i.ytimg.com/vi/mKuoc0ZbKug/hqdefault.jpg",
                    "width": 480,
                    "height": 360
                }
            },
            "channelTitle": "Cleveland Clinic",
            "liveBroadcastContent": "none"
        }
    },
    {
        "kind": "youtube#searchResult",
        "etag": "\"nxOHAKTVB7baOKsQgTtJIyGxcs8/wtrO08JYb50BI56C9grUrm0pVoE\"",
        "id": {
            "kind": "youtube#video",
            "videoId": "oSRtTclbtsE"
        },
        "snippet": {
            "publishedAt": "2019-04-18T20:07:52.000Z",
            "channelId": "UCNjDofziwuV2ffxv9p258-w",
            "title": "Tonsils and Adenoids Surgery",
            "description": "To learn more about tonsillectomies, visit: ...",
            "thumbnails": {
                "default": {
                    "url": "https://i.ytimg.com/vi/oSRtTclbtsE/default.jpg",
                    "width": 120,
                    "height": 90
                },
                "medium": {
                    "url": "https://i.ytimg.com/vi/oSRtTclbtsE/mqdefault.jpg",
                    "width": 320,
                    "height": 180
                },
                "high": {
                    "url": "https://i.ytimg.com/vi/oSRtTclbtsE/hqdefault.jpg",
                    "width": 480,
                    "height": 360
                }
            },
            "channelTitle": "Children's Hospital Colorado",
            "liveBroadcastContent": "none"
        }
    },
    {
        "kind": "youtube#searchResult",
        "etag": "\"nxOHAKTVB7baOKsQgTtJIyGxcs8/dXWkQj_1WbtIGbPxZn4VriOovx4\"",
        "id": {
            "kind": "youtube#video",
            "videoId": "eDmlWAaDxVg"
        },
        "snippet": {
            "publishedAt": "2020-02-11T19:19:31.000Z",
            "channelId": "UC8hzWaP0JfFJ8a1UjLIl1FA",
            "title": "Open Heart Surgery | Inside the OR",
            "description": "Tough to beat! Head #InsideTheOR with S. Christopher Malaisrie, MD, and witness open heart surgery by one of the best cardiology and heart surgery programs ...",
            "thumbnails": {
                "default": {
                    "url": "https://i.ytimg.com/vi/eDmlWAaDxVg/default.jpg",
                    "width": 120,
                    "height": 90
                },
                "medium": {
                    "url": "https://i.ytimg.com/vi/eDmlWAaDxVg/mqdefault.jpg",
                    "width": 320,
                    "height": 180
                },
                "high": {
                    "url": "https://i.ytimg.com/vi/eDmlWAaDxVg/hqdefault.jpg",
                    "width": 480,
                    "height": 360
                }
            },
            "channelTitle": "Northwestern Medicine",
            "liveBroadcastContent": "none"
        }
    },
    {
        "kind": "youtube#searchResult",
        "etag": "\"nxOHAKTVB7baOKsQgTtJIyGxcs8/PNAeKY3ZIt80aKTFx9q4DsUarS8\"",
        "id": {
            "kind": "youtube#video",
            "videoId": "TtPbyHRUuaE"
        },
        "snippet": {
            "publishedAt": "2018-12-09T13:00:06.000Z",
            "channelId": "UC2vlpX8sNDBmPcY_1_QSGJg",
            "title": "Can Surgery Help Remove This Boy&#39;s Life-Threatening Fibroma? | Body Bizarre",
            "description": "Amar has a large ossifying fibroma growing out of his face that is proving to be life-threatening. So, he's undergoing complex surgery to remove his fibroma and ...",
            "thumbnails": {
                "default": {
                    "url": "https://i.ytimg.com/vi/TtPbyHRUuaE/default.jpg",
                    "width": 120,
                    "height": 90
                },
                "medium": {
                    "url": "https://i.ytimg.com/vi/TtPbyHRUuaE/mqdefault.jpg",
                    "width": 320,
                    "height": 180
                },
                "high": {
                    "url": "https://i.ytimg.com/vi/TtPbyHRUuaE/hqdefault.jpg",
                    "width": 480,
                    "height": 360
                }
            },
            "channelTitle": "tlc uk",
            "liveBroadcastContent": "none"
        }
    },
    {
        "kind": "youtube#searchResult",
        "etag": "\"nxOHAKTVB7baOKsQgTtJIyGxcs8/dvyj2TjqfC_PRwuelKz3KqLh_70\"",
        "id": {
            "kind": "youtube#video",
            "videoId": "Vl5Q5Xd66g4"
        },
        "snippet": {
            "publishedAt": "2020-04-02T11:00:12.000Z",
            "channelId": "UC2vlpX8sNDBmPcY_1_QSGJg",
            "title": "Dr Lee Arranges A Free Surgery For This Patient | Dr. Pimple Popper",
            "description": "Delano visits Dr. Lee 18 because his lymphangioma has come back. But she has a big surprise for him. Subscribe to TLC UK for more great clips: ...",
            "thumbnails": {
                "default": {
                    "url": "https://i.ytimg.com/vi/Vl5Q5Xd66g4/default.jpg",
                    "width": 120,
                    "height": 90
                },
                "medium": {
                    "url": "https://i.ytimg.com/vi/Vl5Q5Xd66g4/mqdefault.jpg",
                    "width": 320,
                    "height": 180
                },
                "high": {
                    "url": "https://i.ytimg.com/vi/Vl5Q5Xd66g4/hqdefault.jpg",
                    "width": 480,
                    "height": 360
                }
            },
            "channelTitle": "tlc uk",
            "liveBroadcastContent": "none"
        }
    },
    {
        "kind": "youtube#searchResult",
        "etag": "\"nxOHAKTVB7baOKsQgTtJIyGxcs8/ZqkQf6xDHh6bf52zWaoSrsLQtY4\"",
        "id": {
            "kind": "youtube#video",
            "videoId": "A0Q0XmmoMlo"
        },
        "snippet": {
            "publishedAt": "2014-09-12T16:18:59.000Z",
            "channelId": "UCHcWYywbgz9GGLniP1h3dxA",
            "title": "Lung Transplant Surgery",
            "description": "Contains Images from Surgery** Dr. Chadrick Denlinger, MUSC transplant surgeon, describes what must take place when a patient receives a lung transplant.",
            "thumbnails": {
                "default": {
                    "url": "https://i.ytimg.com/vi/A0Q0XmmoMlo/default.jpg",
                    "width": 120,
                    "height": 90
                },
                "medium": {
                    "url": "https://i.ytimg.com/vi/A0Q0XmmoMlo/mqdefault.jpg",
                    "width": 320,
                    "height": 180
                },
                "high": {
                    "url": "https://i.ytimg.com/vi/A0Q0XmmoMlo/hqdefault.jpg",
                    "width": 480,
                    "height": 360
                }
            },
            "channelTitle": "MUSC PR",
            "liveBroadcastContent": "none"
        }
    },
    {
        "kind": "youtube#searchResult",
        "etag": "\"nxOHAKTVB7baOKsQgTtJIyGxcs8/6I5Nz7nnD01V0Nocvzm3H5bpHQ8\"",
        "id": {
            "kind": "youtube#video",
            "videoId": "_vyNtvDQ4Lw"
        },
        "snippet": {
            "publishedAt": "2013-10-07T19:06:53.000Z",
            "channelId": "UC85VW73bQLEjs_taFKP7TwQ",
            "title": "Neck Surgery | Cervical Laminectomy | Nucleus Health",
            "description": "Hospitals can license this animation for patient education and content marketing initiatives. Learn more: ...",
            "thumbnails": {
                "default": {
                    "url": "https://i.ytimg.com/vi/_vyNtvDQ4Lw/default.jpg",
                    "width": 120,
                    "height": 90
                },
                "medium": {
                    "url": "https://i.ytimg.com/vi/_vyNtvDQ4Lw/mqdefault.jpg",
                    "width": 320,
                    "height": 180
                },
                "high": {
                    "url": "https://i.ytimg.com/vi/_vyNtvDQ4Lw/hqdefault.jpg",
                    "width": 480,
                    "height": 360
                }
            },
            "channelTitle": "Nucleus Medical Media",
            "liveBroadcastContent": "none"
        }
    },
    {
        "kind": "youtube#searchResult",
        "etag": "\"nxOHAKTVB7baOKsQgTtJIyGxcs8/UqhAlXPvwWtP2M6OJiZLP_tlpRY\"",
        "id": {
            "kind": "youtube#video",
            "videoId": "Ge1-Xm8IVEQ"
        },
        "snippet": {
            "publishedAt": "2019-02-06T16:00:02.000Z",
            "channelId": "UCsZsDjpf2Ppv_cT2K6_q2cw",
            "title": "What Getting Laser Eye Surgery Is Really Like | Macro Beauty | Refinery29",
            "description": "On this week's episode of Macro Beauty, we follow a young woman on her journey to getting Lasik eye surgery. She opts for this corrective vision procedure and ...",
            "thumbnails": {
                "default": {
                    "url": "https://i.ytimg.com/vi/Ge1-Xm8IVEQ/default.jpg",
                    "width": 120,
                    "height": 90
                },
                "medium": {
                    "url": "https://i.ytimg.com/vi/Ge1-Xm8IVEQ/mqdefault.jpg",
                    "width": 320,
                    "height": 180
                },
                "high": {
                    "url": "https://i.ytimg.com/vi/Ge1-Xm8IVEQ/hqdefault.jpg",
                    "width": 480,
                    "height": 360
                }
            },
            "channelTitle": "Refinery29",
            "liveBroadcastContent": "none"
        }
    },
    {
        "kind": "youtube#searchResult",
        "etag": "\"nxOHAKTVB7baOKsQgTtJIyGxcs8/cCraNbkTiaPHkWADeyE-FWLDSgY\"",
        "id": {
            "kind": "youtube#video",
            "videoId": "qd6C4ISF9JU"
        },
        "snippet": {
            "publishedAt": "2019-11-18T22:00:13.000Z",
            "channelId": "UCn8zNIfYAQNdrFRrr8oibKw",
            "title": "Surgery for Six Packs: The Rise of Male Plastic Surgery",
            "description": "VICE follows two men getting cosmetic surgery. One man is getting liposuction on his abdominal area to get the six pack he always wanted. The other visits The ...",
            "thumbnails": {
                "default": {
                    "url": "https://i.ytimg.com/vi/qd6C4ISF9JU/default.jpg",
                    "width": 120,
                    "height": 90
                },
                "medium": {
                    "url": "https://i.ytimg.com/vi/qd6C4ISF9JU/mqdefault.jpg",
                    "width": 320,
                    "height": 180
                },
                "high": {
                    "url": "https://i.ytimg.com/vi/qd6C4ISF9JU/hqdefault.jpg",
                    "width": 480,
                    "height": 360
                }
            },
            "channelTitle": "VICE",
            "liveBroadcastContent": "none"
        }
    },
    {
        "kind": "youtube#searchResult",
        "etag": "\"nxOHAKTVB7baOKsQgTtJIyGxcs8/0VaFDeIX2GlQ4jiXsRBTebDSPVA\"",
        "id": {
            "kind": "youtube#video",
            "videoId": "U7g6QAOCJkQ"
        },
        "snippet": {
            "publishedAt": "2019-11-26T18:00:05.000Z",
            "channelId": "UCcjoLhqu3nyOFmdqF17LeBQ",
            "title": "Would You Have A Nose Job After Watching This? | Plastic Surgery Undressed",
            "description": "Full episode on iPlayer: https://bbc.in/2OklOH5 Four people planning to undergo a nose job get more than they bargain for with a live view of the operation, ...",
            "thumbnails": {
                "default": {
                    "url": "https://i.ytimg.com/vi/U7g6QAOCJkQ/default.jpg",
                    "width": 120,
                    "height": 90
                },
                "medium": {
                    "url": "https://i.ytimg.com/vi/U7g6QAOCJkQ/mqdefault.jpg",
                    "width": 320,
                    "height": 180
                },
                "high": {
                    "url": "https://i.ytimg.com/vi/U7g6QAOCJkQ/hqdefault.jpg",
                    "width": 480,
                    "height": 360
                }
            },
            "channelTitle": "BBC Three",
            "liveBroadcastContent": "none"
        }
    },
    {
        "kind": "youtube#searchResult",
        "etag": "\"nxOHAKTVB7baOKsQgTtJIyGxcs8/87J88STbxFlLJdmbulQ1u50Jg2U\"",
        "id": {
            "kind": "youtube#video",
            "videoId": "pEtdAarcqzI"
        },
        "snippet": {
            "publishedAt": "2017-08-25T16:49:34.000Z",
            "channelId": "UCAK06bAz_B8pFWG5qBIZS6g",
            "title": "Back Cyst Removal - Dr. Paul Ruff | West End Plastic Surgery",
            "description": "Dr. Paul Ruff of West End Plastic Surgery removing a huge back cyst from a patient. The cyst has been bothering the patient for quite some time - Not anymore!",
            "thumbnails": {
                "default": {
                    "url": "https://i.ytimg.com/vi/pEtdAarcqzI/default.jpg",
                    "width": 120,
                    "height": 90
                },
                "medium": {
                    "url": "https://i.ytimg.com/vi/pEtdAarcqzI/mqdefault.jpg",
                    "width": 320,
                    "height": 180
                },
                "high": {
                    "url": "https://i.ytimg.com/vi/pEtdAarcqzI/hqdefault.jpg",
                    "width": 480,
                    "height": 360
                }
            },
            "channelTitle": "West End Plastic Surgery",
            "liveBroadcastContent": "none"
        }
    },
    {
        "kind": "youtube#searchResult",
        "etag": "\"nxOHAKTVB7baOKsQgTtJIyGxcs8/BRf0fJNWfO5d5DLLyYJBFbtteII\"",
        "id": {
            "kind": "youtube#video",
            "videoId": "WCyANtdARBQ"
        },
        "snippet": {
            "publishedAt": "2020-04-16T21:59:48.000Z",
            "channelId": "UCNpeFIjuR24mQCUtVFIEDpQ",
            "title": "Cardiothoracic Surgery in the COVID Crisis: Stratifying Patients for Cardiac Operations",
            "description": "The COVID pandemic is changing cardiothoracic surgery practice and may lead to a prolonged need for procedural deferral. This week's special COVID webinar ...",
            "thumbnails": {
                "default": {
                    "url": "https://i.ytimg.com/vi/WCyANtdARBQ/default.jpg",
                    "width": 120,
                    "height": 90
                },
                "medium": {
                    "url": "https://i.ytimg.com/vi/WCyANtdARBQ/mqdefault.jpg",
                    "width": 320,
                    "height": 180
                },
                "high": {
                    "url": "https://i.ytimg.com/vi/WCyANtdARBQ/hqdefault.jpg",
                    "width": 480,
                    "height": 360
                }
            },
            "channelTitle": "ThoracicSurgeons",
            "liveBroadcastContent": "none"
        }
    },
    {
        "kind": "youtube#searchResult",
        "etag": "\"nxOHAKTVB7baOKsQgTtJIyGxcs8/f7VYDuGZVBtQrXi-HyA8derH2l0\"",
        "id": {
            "kind": "youtube#video",
            "videoId": "VGBUFZMC5VU"
        },
        "snippet": {
            "publishedAt": "2019-12-19T15:22:05.000Z",
            "channelId": "UCAK06bAz_B8pFWG5qBIZS6g",
            "title": "Breast Augmentation with Silicone Implants - Dr. Paul Ruff | West End Plastic Surgery",
            "description": "Dr. Ruff's performing a breast augmentation using the Keller Funnel aka the \"No-Touch\" technique. Keller Funnel allows for a safe, quick and efficient insertion of ...",
            "thumbnails": {
                "default": {
                    "url": "https://i.ytimg.com/vi/VGBUFZMC5VU/default.jpg",
                    "width": 120,
                    "height": 90
                },
                "medium": {
                    "url": "https://i.ytimg.com/vi/VGBUFZMC5VU/mqdefault.jpg",
                    "width": 320,
                    "height": 180
                },
                "high": {
                    "url": "https://i.ytimg.com/vi/VGBUFZMC5VU/hqdefault.jpg",
                    "width": 480,
                    "height": 360
                }
            },
            "channelTitle": "West End Plastic Surgery",
            "liveBroadcastContent": "none"
        }
    },
    {
        "kind": "youtube#searchResult",
        "etag": "\"nxOHAKTVB7baOKsQgTtJIyGxcs8/QplEEeFh71WS3xhS0_2R4SaKySw\"",
        "id": {
            "kind": "youtube#video",
            "videoId": "xRq84TIGQjU"
        },
        "snippet": {
            "publishedAt": "2020-04-16T14:06:04.000Z",
            "channelId": "UCgNOQP5BvrzQJ_vhRo7VN1Q",
            "title": "Jonnie&#39;s weight loss struggles end after successful weight loss surgery",
            "description": "Learn more about bariatric surgery at Beaumont: https://www.beaumont.org/bariatric.",
            "thumbnails": {
                "default": {
                    "url": "https://i.ytimg.com/vi/xRq84TIGQjU/default.jpg",
                    "width": 120,
                    "height": 90
                },
                "medium": {
                    "url": "https://i.ytimg.com/vi/xRq84TIGQjU/mqdefault.jpg",
                    "width": 320,
                    "height": 180
                },
                "high": {
                    "url": "https://i.ytimg.com/vi/xRq84TIGQjU/hqdefault.jpg",
                    "width": 480,
                    "height": 360
                }
            },
            "channelTitle": "Beaumont Health",
            "liveBroadcastContent": "none"
        }
    },
    {
        "kind": "youtube#searchResult",
        "etag": "\"nxOHAKTVB7baOKsQgTtJIyGxcs8/sQR3l-OZ7i3if8rCdbRovNvmigE\"",
        "id": {
            "kind": "youtube#video",
            "videoId": "QvkQzUN4PN4"
        },
        "snippet": {
            "publishedAt": "2020-02-22T12:34:27.000Z",
            "channelId": "UC9k-yiEpRHMNVOnOi_aQK8w",
            "title": "Man Gets Limb-Lengthening Surgery to Be Taller",
            "description": "One man made a special trip to Las Vegas with his wife, but he's not hoping to strike it rich. He's here to get taller. Ryan Wade is 5-foot-7, just two inches shorter ...",
            "thumbnails": {
                "default": {
                    "url": "https://i.ytimg.com/vi/QvkQzUN4PN4/default.jpg",
                    "width": 120,
                    "height": 90
                },
                "medium": {
                    "url": "https://i.ytimg.com/vi/QvkQzUN4PN4/mqdefault.jpg",
                    "width": 320,
                    "height": 180
                },
                "high": {
                    "url": "https://i.ytimg.com/vi/QvkQzUN4PN4/hqdefault.jpg",
                    "width": 480,
                    "height": 360
                }
            },
            "channelTitle": "Inside Edition",
            "liveBroadcastContent": "none"
        }
    },
    {
        "kind": "youtube#searchResult",
        "etag": "\"nxOHAKTVB7baOKsQgTtJIyGxcs8/ylC-hd0vdvoQThrR_iGL7uR-tjw\"",
        "id": {
            "kind": "youtube#video",
            "videoId": "RZMKC6KWUC8"
        },
        "snippet": {
            "publishedAt": "2020-01-21T22:51:43.000Z",
            "channelId": "UC9k-yiEpRHMNVOnOi_aQK8w",
            "title": "4 Kids Who Got Plastic Surgery",
            "description": "Plastic surgery isn't just for people of a certain age; sometimes young people get cosmetic procedures, as well. California Teen Elisa Chaddock wasn't looking ...",
            "thumbnails": {
                "default": {
                    "url": "https://i.ytimg.com/vi/RZMKC6KWUC8/default.jpg",
                    "width": 120,
                    "height": 90
                },
                "medium": {
                    "url": "https://i.ytimg.com/vi/RZMKC6KWUC8/mqdefault.jpg",
                    "width": 320,
                    "height": 180
                },
                "high": {
                    "url": "https://i.ytimg.com/vi/RZMKC6KWUC8/hqdefault.jpg",
                    "width": 480,
                    "height": 360
                }
            },
            "channelTitle": "Inside Edition",
            "liveBroadcastContent": "none"
        }
    },
    {
        "kind": "youtube#searchResult",
        "etag": "\"nxOHAKTVB7baOKsQgTtJIyGxcs8/CkCYwvTmS-X-Ynq5O4Murx_yDlk\"",
        "id": {
            "kind": "youtube#video",
            "videoId": "f0EK91tfM7I"
        },
        "snippet": {
            "publishedAt": "2017-12-15T21:13:37.000Z",
            "channelId": "UCpCWvDDoumrtOUsV9p2A0Qg",
            "title": "EXTREME INFECTED INGROWN TOENAIL REMOVAL OF DEFORMED TOENAIL SURGERY",
            "description": "Patient has been suffering from reoccurring ingrown toenails in his left big toe. The toe has become extremely large and deformed due to reoccurring toe ...",
            "thumbnails": {
                "default": {
                    "url": "https://i.ytimg.com/vi/f0EK91tfM7I/default.jpg",
                    "width": 120,
                    "height": 90
                },
                "medium": {
                    "url": "https://i.ytimg.com/vi/f0EK91tfM7I/mqdefault.jpg",
                    "width": 320,
                    "height": 180
                },
                "high": {
                    "url": "https://i.ytimg.com/vi/f0EK91tfM7I/hqdefault.jpg",
                    "width": 480,
                    "height": 360
                }
            },
            "channelTitle": "The Toe Bro",
            "liveBroadcastContent": "none"
        }
    }
]